{
  "version": "3.1.1",
  "flags": {},
  "shapes": [
    {
      "kie_linking": [],
      "label": "2",
      "score": 0.6442532539367676,
      "points": [
        [
          656.7106819152832,
          856.1048746109009
        ],
        [
          685.215015411377,
          856.1048746109009
        ],
        [
          685.215015411377,
          883.2194089889526
        ],
        [
          656.7106819152832,
          883.2194089889526
        ]
      ],
      "group_id": null,
      "description": null,
      "difficult": false,
      "shape_type": "rectangle",
      "flags": {},
      "attributes": {}
    },
    {
      "kie_linking": [],
      "label": "2",
      "score": 0.6380227208137512,
      "points": [
        [
          625.1373195648193,
          850.4560995101929
        ],
        [
          655.5102396011353,
          850.4560995101929
        ],
        [
          655.5102396011353,
          878.0180835723877
        ],
        [
          625.1373195648193,
          878.0180835723877
        ]
      ],
      "group_id": null,
      "description": null,
      "difficult": false,
      "shape_type": "rectangle",
      "flags": {},
      "attributes": {}
    },
    {
      "kie_linking": [],
      "label": "2",
      "score": 0.5770836472511292,
      "points": [
        [
          750.411627292633,
          843.5267639160156
        ],
        [
          777.5431609153748,
          843.5267639160156
        ],
        [
          777.5431609153748,
          871.2216377258301
        ],
        [
          750.411627292633,
          871.2216377258301
        ]
      ],
      "group_id": null,
      "description": null,
      "difficult": false,
      "shape_type": "rectangle",
      "flags": {},
      "attributes": {}
    },
    {
      "kie_linking": [],
      "label": "2",
      "score": 0.5681617259979248,
      "points": [
        [
          774.3201780319214,
          863.408637046814
        ],
        [
          804.3420267105103,
          863.408637046814
        ],
        [
          804.3420267105103,
          889.9443101882935
        ],
        [
          774.3201780319214,
          889.9443101882935
        ]
      ],
      "group_id": null,
      "description": null,
      "difficult": false,
      "shape_type": "rectangle",
      "flags": {},
      "attributes": {}
    },
    {
      "kie_linking": [],
      "label": "2",
      "score": 0.5076676607131958,
      "points": [
        [
          602.7782869338989,
          836.4120626449585
        ],
        [
          633.1062698364258,
          836.4120626449585
        ],
        [
          633.1062698364258,
          862.6741218566895
        ],
        [
          602.7782869338989,
          862.6741218566895
        ]
      ],
      "group_id": null,
      "description": null,
      "difficult": false,
      "shape_type": "rectangle",
      "flags": {},
      "attributes": {}
    },
    {
      "kie_linking": [],
      "label": "3",
      "score": 0.4993398189544678,
      "points": [
        [
          654.0488958358765,
          663.9251613616943
        ],
        [
          680.3269195556641,
          663.9251613616943
        ],
        [
          680.3269195556641,
          688.1130170822144
        ],
        [
          654.0488958358765,
          688.1130170822144
        ]
      ],
      "group_id": null,
      "description": null,
      "difficult": false,
      "shape_type": "rectangle",
      "flags": {},
      "attributes": {}
    },
    {
      "kie_linking": [],
      "label": "2",
      "score": 0.4927397072315216,
      "points": [
        [
          717.6844596862793,
          840.3568482398987
        ],
        [
          745.1401615142822,
          840.3568482398987
        ],
        [
          745.1401615142822,
          866.7160248756409
        ],
        [
          717.6844596862793,
          866.7160248756409
        ]
      ],
      "group_id": null,
      "description": null,
      "difficult": false,
      "shape_type": "rectangle",
      "flags": {},
      "attributes": {}
    },
    {
      "kie_linking": [],
      "label": "2",
      "score": 0.48487553000450134,
      "points": [
        [
          682.9969096183777,
          830.9788823127747
        ],
        [
          709.7257828712463,
          830.9788823127747
        ],
        [
          709.7257828712463,
          856.0298562049866
        ],
        [
          682.9969096183777,
          856.0298562049866
        ]
      ],
      "group_id": null,
      "description": null,
      "difficult": false,
      "shape_type": "rectangle",
      "flags": {},
      "attributes": {}
    },
    {
      "kie_linking": [],
      "label": "2",
      "score": 0.46980294585227966,
      "points": [
        [
          690.2707386016846,
          859.3076801300049
        ],
        [
          722.083568572998,
          859.3076801300049
        ],
        [
          722.083568572998,
          887.9775714874268
        ],
        [
          690.2707386016846,
          887.9775714874268
        ]
      ],
      "group_id": null,
      "description": null,
      "difficult": false,
      "shape_type": "rectangle",
      "flags": {},
      "attributes": {}
    },
    {
      "kie_linking": [],
      "label": "2",
      "score": 0.43728628754615784,
      "points": [
        [
          594.3827295303345,
          676.6790294647217
        ],
        [
          622.7564644813538,
          676.6790294647217
        ],
        [
          622.7564644813538,
          703.5747909545898
        ],
        [
          594.3827295303345,
          703.5747909545898
        ]
      ],
      "group_id": null,
      "description": null,
      "difficult": false,
      "shape_type": "rectangle",
      "flags": {},
      "attributes": {}
    },
    {
      "kie_linking": [],
      "label": "2",
      "score": 0.4328695237636566,
      "points": [
        [
          649.6395134925842,
          816.8625617027283
        ],
        [
          681.0754036903381,
          816.8625617027283
        ],
        [
          681.0754036903381,
          843.1847834587097
        ],
        [
          649.6395134925842,
          843.1847834587097
        ]
      ],
      "group_id": null,
      "description": null,
      "difficult": false,
      "shape_type": "rectangle",
      "flags": {},
      "attributes": {}
    },
    {
      "kie_linking": [],
      "label": "2",
      "score": 0.42145949602127075,
      "points": [
        [
          547.6436388492584,
          725.0809049606323
        ],
        [
          576.5902483463287,
          725.0809049606323
        ],
        [
          576.5902483463287,
          749.6535348892212
        ],
        [
          547.6436388492584,
          749.6535348892212
        ]
      ],
      "group_id": null,
      "description": null,
      "difficult": false,
      "shape_type": "rectangle",
      "flags": {},
      "attributes": {}
    },
    {
      "kie_linking": [],
      "label": "2",
      "score": 0.38899946212768555,
      "points": [
        [
          513.682621717453,
          714.5747804641724
        ],
        [
          543.3870279788971,
          714.5747804641724
        ],
        [
          543.3870279788971,
          742.4344730377197
        ],
        [
          513.682621717453,
          742.4344730377197
        ]
      ],
      "group_id": null,
      "description": null,
      "difficult": false,
      "shape_type": "rectangle",
      "flags": {},
      "attributes": {}
    },
    {
      "kie_linking": [],
      "label": "2",
      "score": 0.3695765733718872,
      "points": [
        [
          558.0708277225494,
          677.6459169387817
        ],
        [
          588.2113754749298,
          677.6459169387817
        ],
        [
          588.2113754749298,
          702.0178079605103
        ],
        [
          558.0708277225494,
          702.0178079605103
        ]
      ],
      "group_id": null,
      "description": null,
      "difficult": false,
      "shape_type": "rectangle",
      "flags": {},
      "attributes": {}
    },
    {
      "kie_linking": [],
      "label": "3",
      "score": 0.3391597867012024,
      "points": [
        [
          665.2301120758057,
          732.8748369216919
        ],
        [
          695.962381362915,
          732.8748369216919
        ],
        [
          695.962381362915,
          758.2003116607666
        ],
        [
          665.2301120758057,
          758.2003116607666
        ]
      ],
      "group_id": null,
      "description": null,
      "difficult": false,
      "shape_type": "rectangle",
      "flags": {},
      "attributes": {}
    },
    {
      "kie_linking": [],
      "label": "2",
      "score": 0.3391385078430176,
      "points": [
        [
          761.3639450073242,
          791.8164658546448
        ],
        [
          789.5327281951904,
          791.8164658546448
        ],
        [
          789.5327281951904,
          815.6065392494202
        ],
        [
          761.3639450073242,
          815.6065392494202
        ]
      ],
      "group_id": null,
      "description": null,
      "difficult": false,
      "shape_type": "rectangle",
      "flags": {},
      "attributes": {}
    },
    {
      "kie_linking": [],
      "label": "2",
      "score": 0.3165421485900879,
      "points": [
        [
          744.3331408500671,
          815.4073524475098
        ],
        [
          771.5300107002258,
          815.4073524475098
        ],
        [
          771.5300107002258,
          838.0042266845703
        ],
        [
          744.3331408500671,
          838.0042266845703
        ]
      ],
      "group_id": null,
      "description": null,
      "difficult": false,
      "shape_type": "rectangle",
      "flags": {},
      "attributes": {}
    },
    {
      "kie_linking": [],
      "label": "2",
      "score": 0.31147730350494385,
      "points": [
        [
          577.8432035446167,
          710.6386423110962
        ],
        [
          605.293288230896,
          710.6386423110962
        ],
        [
          605.293288230896,
          735.9948635101318
        ],
        [
          577.8432035446167,
          735.9948635101318
        ]
      ],
      "group_id": null,
      "description": null,
      "difficult": false,
      "shape_type": "rectangle",
      "flags": {},
      "attributes": {}
    },
    {
      "kie_linking": [],
      "label": "2",
      "score": 0.3106034994125366,
      "points": [
        [
          606.3496804237366,
          802.8249549865723
        ],
        [
          639.1243720054626,
          802.8249549865723
        ],
        [
          639.1243720054626,
          830.7838344573975
        ],
        [
          606.3496804237366,
          830.7838344573975
        ]
      ],
      "group_id": null,
      "description": null,
      "difficult": false,
      "shape_type": "rectangle",
      "flags": {},
      "attributes": {}
    },
    {
      "kie_linking": [],
      "label": "2",
      "score": 0.3041505813598633,
      "points": [
        [
          579.2732095718384,
          740.9570169448853
        ],
        [
          609.4459080696106,
          740.9570169448853
        ],
        [
          609.4459080696106,
          762.9992723464966
        ],
        [
          579.2732095718384,
          762.9992723464966
        ]
      ],
      "group_id": null,
      "description": null,
      "difficult": false,
      "shape_type": "rectangle",
      "flags": {},
      "attributes": {}
    },
    {
      "kie_linking": [],
      "label": "2+",
      "score": 0.27951207756996155,
      "points": [
        [
          676.0258889198303,
          704.1923809051514
        ],
        [
          708.1065678596497,
          704.1923809051514
        ],
        [
          708.1065678596497,
          727.7672290802002
        ],
        [
          676.0258889198303,
          727.7672290802002
        ]
      ],
      "group_id": null,
      "description": null,
      "difficult": false,
      "shape_type": "rectangle",
      "flags": {},
      "attributes": {}
    },
    {
      "kie_linking": [],
      "label": "2",
      "score": 0.26558369398117065,
      "points": [
        [
          560.7950305938721,
          768.554995059967
        ],
        [
          594.4760775566101,
          768.554995059967
        ],
        [
          594.4760775566101,
          806.3137173652649
        ],
        [
          560.7950305938721,
          806.3137173652649
        ]
      ],
      "group_id": null,
      "description": null,
      "difficult": false,
      "shape_type": "rectangle",
      "flags": {},
      "attributes": {}
    },
    {
      "kie_linking": [],
      "label": "3",
      "score": 0.26249784231185913,
      "points": [
        [
          639.6030855178833,
          755.6792497634888
        ],
        [
          669.7128868103027,
          755.6792497634888
        ],
        [
          669.7128868103027,
          780.6252717971802
        ],
        [
          639.6030855178833,
          780.6252717971802
        ]
      ],
      "group_id": null,
      "description": null,
      "difficult": false,
      "shape_type": "rectangle",
      "flags": {},
      "attributes": {}
    },
    {
      "label": "2+",
      "score": null,
      "points": [
        [
          629.375,
          679.3749999999999
        ],
        [
          659.5833333333333,
          679.3749999999999
        ],
        [
          659.5833333333333,
          701.2499999999999
        ],
        [
          629.375,
          701.2499999999999
        ]
      ],
      "group_id": null,
      "description": "",
      "difficult": false,
      "shape_type": "rectangle",
      "flags": {},
      "attributes": {},
      "kie_linking": []
    },
    {
      "label": "2+",
      "score": null,
      "points": [
        [
          606.4583333333333,
          717.9166666666666
        ],
        [
          635.625,
          717.9166666666666
        ],
        [
          635.625,
          738.7499999999999
        ],
        [
          606.4583333333333,
          738.7499999999999
        ]
      ],
      "group_id": null,
      "description": "",
      "difficult": false,
      "shape_type": "rectangle",
      "flags": {},
      "attributes": {},
      "kie_linking": []
    },
    {
      "label": "2+",
      "score": null,
      "points": [
        [
          622.0833333333333,
          732.4999999999999
        ],
        [
          654.375,
          732.4999999999999
        ],
        [
          654.375,
          755.4166666666666
        ],
        [
          622.0833333333333,
          755.4166666666666
        ]
      ],
      "group_id": null,
      "description": "",
      "difficult": false,
      "shape_type": "rectangle",
      "flags": {},
      "attributes": {},
      "kie_linking": []
    },
    {
      "label": "2+",
      "score": null,
      "points": [
        [
          670.0,
          777.2916666666666
        ],
        [
          712.7083333333333,
          777.2916666666666
        ],
        [
          712.7083333333333,
          799.1666666666666
        ],
        [
          670.0,
          799.1666666666666
        ]
      ],
      "group_id": null,
      "description": "",
      "difficult": false,
      "shape_type": "rectangle",
      "flags": {},
      "attributes": {},
      "kie_linking": []
    }
  ],
  "imagePath": "20241107113709725.bmp",
  "imageData": null,
  "imageHeight": 1240,
  "imageWidth": 1240,
  "description": ""
}