{
  "version": "3.1.1",
  "flags": {},
  "shapes": [
    {
      "kie_linking": [],
      "label": "2+",
      "score": 0.7742146253585815,
      "points": [
        [
          278.9178419113159,
          588.8877236843109
        ],
        [
          309.6294164657593,
          588.8877236843109
        ],
        [
          309.6294164657593,
          619.8317444324493
        ],
        [
          278.9178419113159,
          619.8317444324493
        ]
      ],
      "group_id": null,
      "description": null,
      "difficult": false,
      "shape_type": "rectangle",
      "flags": {},
      "attributes": {}
    },
    {
      "kie_linking": [],
      "label": "2+",
      "score": 0.7483593225479126,
      "points": [
        [
          129.8376441001892,
          557.7098155021667
        ],
        [
          159.43092703819275,
          557.7098155021667
        ],
        [
          159.43092703819275,
          588.4988474845886
        ],
        [
          129.8376441001892,
          588.4988474845886
        ]
      ],
      "group_id": null,
      "description": null,
      "difficult": false,
      "shape_type": "rectangle",
      "flags": {},
      "attributes": {}
    },
    {
      "kie_linking": [],
      "label": "2+",
      "score": 0.6901115775108337,
      "points": [
        [
          275.38724660873413,
          635.453052520752
        ],
        [
          303.7281656265259,
          635.453052520752
        ],
        [
          303.7281656265259,
          662.9185104370117
        ],
        [
          275.38724660873413,
          662.9185104370117
        ]
      ],
      "group_id": null,
      "description": null,
      "difficult": false,
      "shape_type": "rectangle",
      "flags": {},
      "attributes": {}
    },
    {
      "kie_linking": [],
      "label": "2+",
      "score": 0.6891511678695679,
      "points": [
        [
          227.34010100364685,
          722.8649425506592
        ],
        [
          260.2041494846344,
          722.8649425506592
        ],
        [
          260.2041494846344,
          752.3067474365234
        ],
        [
          227.34010100364685,
          752.3067474365234
        ]
      ],
      "group_id": null,
      "description": null,
      "difficult": false,
      "shape_type": "rectangle",
      "flags": {},
      "attributes": {}
    },
    {
      "kie_linking": [],
      "label": "2+",
      "score": 0.6854415535926819,
      "points": [
        [
          193.54284942150116,
          689.7540354728699
        ],
        [
          219.45816099643707,
          689.7540354728699
        ],
        [
          219.45816099643707,
          717.6913332939148
        ],
        [
          193.54284942150116,
          717.6913332939148
        ]
      ],
      "group_id": null,
      "description": null,
      "difficult": false,
      "shape_type": "rectangle",
      "flags": {},
      "attributes": {}
    },
    {
      "kie_linking": [],
      "label": "2+",
      "score": 0.6835461258888245,
      "points": [
        [
          186.52103424072266,
          599.8911499977112
        ],
        [
          216.49439811706543,
          599.8911499977112
        ],
        [
          216.49439811706543,
          628.505756855011
        ],
        [
          186.52103424072266,
          628.505756855011
        ]
      ],
      "group_id": null,
      "description": null,
      "difficult": false,
      "shape_type": "rectangle",
      "flags": {},
      "attributes": {}
    },
    {
      "kie_linking": [],
      "label": "2+",
      "score": 0.6779912114143372,
      "points": [
        [
          228.9165222644806,
          588.9387953281403
        ],
        [
          259.5574390888214,
          588.9387953281403
        ],
        [
          259.5574390888214,
          618.4043991565704
        ],
        [
          228.9165222644806,
          618.4043991565704
        ]
      ],
      "group_id": null,
      "description": null,
      "difficult": false,
      "shape_type": "rectangle",
      "flags": {},
      "attributes": {}
    },
    {
      "kie_linking": [],
      "label": "2+",
      "score": 0.6763961911201477,
      "points": [
        [
          190.7597404718399,
          644.7823858261108
        ],
        [
          218.60860526561737,
          644.7823858261108
        ],
        [
          218.60860526561737,
          674.7554540634155
        ],
        [
          190.7597404718399,
          674.7554540634155
        ]
      ],
      "group_id": null,
      "description": null,
      "difficult": false,
      "shape_type": "rectangle",
      "flags": {},
      "attributes": {}
    },
    {
      "kie_linking": [],
      "label": "2+",
      "score": 0.6724915504455566,
      "points": [
        [
          314.8520278930664,
          628.390383720398
        ],
        [
          345.68947076797485,
          628.390383720398
        ],
        [
          345.68947076797485,
          657.3000383377075
        ],
        [
          314.8520278930664,
          657.3000383377075
        ]
      ],
      "group_id": null,
      "description": null,
      "difficult": false,
      "shape_type": "rectangle",
      "flags": {},
      "attributes": {}
    },
    {
      "kie_linking": [],
      "label": "2+",
      "score": 0.6664547920227051,
      "points": [
        [
          216.27429485321045,
          549.2075324058533
        ],
        [
          245.21011352539062,
          549.2075324058533
        ],
        [
          245.21011352539062,
          581.4225792884827
        ],
        [
          216.27429485321045,
          581.4225792884827
        ]
      ],
      "group_id": null,
      "description": null,
      "difficult": false,
      "shape_type": "rectangle",
      "flags": {},
      "attributes": {}
    },
    {
      "kie_linking": [],
      "label": "2+",
      "score": 0.6622819900512695,
      "points": [
        [
          100.63398569822311,
          615.1134192943573
        ],
        [
          131.70631378889084,
          615.1134192943573
        ],
        [
          131.70631378889084,
          643.5609531402588
        ],
        [
          100.63398569822311,
          643.5609531402588
        ]
      ],
      "group_id": null,
      "description": null,
      "difficult": false,
      "shape_type": "rectangle",
      "flags": {},
      "attributes": {}
    },
    {
      "kie_linking": [],
      "label": "2+",
      "score": 0.6476991772651672,
      "points": [
        [
          235.6140398979187,
          681.5972805023193
        ],
        [
          262.1464240550995,
          681.5972805023193
        ],
        [
          262.1464240550995,
          710.5560111999512
        ],
        [
          235.6140398979187,
          710.5560111999512
        ]
      ],
      "group_id": null,
      "description": null,
      "difficult": false,
      "shape_type": "rectangle",
      "flags": {},
      "attributes": {}
    },
    {
      "kie_linking": [],
      "label": "3",
      "score": 0.6383349895477295,
      "points": [
        [
          357.77674674987793,
          1037.9724025726318
        ],
        [
          386.67250633239746,
          1037.9724025726318
        ],
        [
          386.67250633239746,
          1070.6384468078613
        ],
        [
          357.77674674987793,
          1070.6384468078613
        ]
      ],
      "group_id": null,
      "description": null,
      "difficult": false,
      "shape_type": "rectangle",
      "flags": {},
      "attributes": {}
    },
    {
      "kie_linking": [],
      "label": "2+",
      "score": 0.6376292705535889,
      "points": [
        [
          230.4284942150116,
          635.0413012504578
        ],
        [
          259.61756467819214,
          635.0413012504578
        ],
        [
          259.61756467819214,
          665.9414935112
        ],
        [
          230.4284942150116,
          665.9414935112
        ]
      ],
      "group_id": null,
      "description": null,
      "difficult": false,
      "shape_type": "rectangle",
      "flags": {},
      "attributes": {}
    },
    {
      "kie_linking": [],
      "label": "2+",
      "score": 0.634223461151123,
      "points": [
        [
          99.05317604541779,
          781.4206147193909
        ],
        [
          129.13019835948944,
          781.4206147193909
        ],
        [
          129.13019835948944,
          811.1313033103943
        ],
        [
          99.05317604541779,
          811.1313033103943
        ]
      ],
      "group_id": null,
      "description": null,
      "difficult": false,
      "shape_type": "rectangle",
      "flags": {},
      "attributes": {}
    },
    {
      "kie_linking": [],
      "label": "2+",
      "score": 0.6195101737976074,
      "points": [
        [
          6.376436315476894,
          822.71000623703
        ],
        [
          40.30583739280701,
          822.71000623703
        ],
        [
          40.30583739280701,
          855.2875065803528
        ],
        [
          6.376436315476894,
          855.2875065803528
        ]
      ],
      "group_id": null,
      "description": null,
      "difficult": false,
      "shape_type": "rectangle",
      "flags": {},
      "attributes": {}
    },
    {
      "kie_linking": [],
      "label": "2+",
      "score": 0.6189088821411133,
      "points": [
        [
          147.55676984786987,
          817.424201965332
        ],
        [
          181.96046948432922,
          817.424201965332
        ],
        [
          181.96046948432922,
          847.6358509063721
        ],
        [
          147.55676984786987,
          847.6358509063721
        ]
      ],
      "group_id": null,
      "description": null,
      "difficult": false,
      "shape_type": "rectangle",
      "flags": {},
      "attributes": {}
    },
    {
      "kie_linking": [],
      "label": "2+",
      "score": 0.6179213523864746,
      "points": [
        [
          169.77012634277344,
          553.100026845932
        ],
        [
          200.3597128391266,
          553.100026845932
        ],
        [
          200.3597128391266,
          585.6506979465485
        ],
        [
          169.77012634277344,
          585.6506979465485
        ]
      ],
      "group_id": null,
      "description": null,
      "difficult": false,
      "shape_type": "rectangle",
      "flags": {},
      "attributes": {}
    },
    {
      "kie_linking": [],
      "label": "2+",
      "score": 0.6166267991065979,
      "points": [
        [
          150.20324736833572,
          694.357283115387
        ],
        [
          178.527250289917,
          694.357283115387
        ],
        [
          178.527250289917,
          726.904776096344
        ],
        [
          150.20324736833572,
          726.904776096344
        ]
      ],
      "group_id": null,
      "description": null,
      "difficult": false,
      "shape_type": "rectangle",
      "flags": {},
      "attributes": {}
    },
    {
      "kie_linking": [],
      "label": "2+",
      "score": 0.6134554743766785,
      "points": [
        [
          326.3978409767151,
          717.9582214355469
        ],
        [
          358.8327693939209,
          717.9582214355469
        ],
        [
          358.8327693939209,
          747.076301574707
        ],
        [
          326.3978409767151,
          747.076301574707
        ]
      ],
      "group_id": null,
      "description": null,
      "difficult": false,
      "shape_type": "rectangle",
      "flags": {},
      "attributes": {}
    },
    {
      "kie_linking": [],
      "label": "2+",
      "score": 0.606661856174469,
      "points": [
        [
          37.215120643377304,
          1071.2887048721313
        ],
        [
          68.43442752957344,
          1071.2887048721313
        ],
        [
          68.43442752957344,
          1100.4901552200317
        ],
        [
          37.215120643377304,
          1100.4901552200317
        ]
      ],
      "group_id": null,
      "description": null,
      "difficult": false,
      "shape_type": "rectangle",
      "flags": {},
      "attributes": {}
    },
    {
      "kie_linking": [],
      "label": "2+",
      "score": 0.6029801964759827,
      "points": [
        [
          318.36421966552734,
          1043.6517763137817
        ],
        [
          349.71851348876953,
          1043.6517763137817
        ],
        [
          349.71851348876953,
          1078.2971239089966
        ],
        [
          318.36421966552734,
          1078.2971239089966
        ]
      ],
      "group_id": null,
      "description": null,
      "difficult": false,
      "shape_type": "rectangle",
      "flags": {},
      "attributes": {}
    },
    {
      "kie_linking": [],
      "label": "2+",
      "score": 0.5925602316856384,
      "points": [
        [
          100.5218368768692,
          740.8156275749207
        ],
        [
          128.42040598392487,
          740.8156275749207
        ],
        [
          128.42040598392487,
          768.8983798027039
        ],
        [
          100.5218368768692,
          768.8983798027039
        ]
      ],
      "group_id": null,
      "description": null,
      "difficult": false,
      "shape_type": "rectangle",
      "flags": {},
      "attributes": {}
    },
    {
      "kie_linking": [],
      "label": "2+",
      "score": 0.5857664942741394,
      "points": [
        [
          185.83177030086517,
          729.359393119812
        ],
        [
          212.8655582666397,
          729.359393119812
        ],
        [
          212.8655582666397,
          760.1228523254395
        ],
        [
          185.83177030086517,
          760.1228523254395
        ]
      ],
      "group_id": null,
      "description": null,
      "difficult": false,
      "shape_type": "rectangle",
      "flags": {},
      "attributes": {}
    },
    {
      "kie_linking": [],
      "label": "2+",
      "score": 0.5851967334747314,
      "points": [
        [
          143.2084184885025,
          605.8895921707153
        ],
        [
          172.85495340824127,
          605.8895921707153
        ],
        [
          172.85495340824127,
          633.2934093475342
        ],
        [
          143.2084184885025,
          633.2934093475342
        ]
      ],
      "group_id": null,
      "description": null,
      "difficult": false,
      "shape_type": "rectangle",
      "flags": {},
      "attributes": {}
    },
    {
      "kie_linking": [],
      "label": "2+",
      "score": 0.5829747319221497,
      "points": [
        [
          271.8869173526764,
          1004.8772382736206
        ],
        [
          305.7449781894684,
          1004.8772382736206
        ],
        [
          305.7449781894684,
          1041.1221408843994
        ],
        [
          271.8869173526764,
          1041.1221408843994
        ]
      ],
      "group_id": null,
      "description": null,
      "difficult": false,
      "shape_type": "rectangle",
      "flags": {},
      "attributes": {}
    },
    {
      "kie_linking": [],
      "label": "2+",
      "score": 0.5815314650535583,
      "points": [
        [
          275.9618949890137,
          1049.9182891845703
        ],
        [
          311.03691697120667,
          1049.9182891845703
        ],
        [
          311.03691697120667,
          1083.0728769302368
        ],
        [
          275.9618949890137,
          1083.0728769302368
        ]
      ],
      "group_id": null,
      "description": null,
      "difficult": false,
      "shape_type": "rectangle",
      "flags": {},
      "attributes": {}
    },
    {
      "kie_linking": [],
      "label": "2+",
      "score": 0.5781981945037842,
      "points": [
        [
          281.1494916677475,
          720.0684928894043
        ],
        [
          309.0480977296829,
          720.0684928894043
        ],
        [
          309.0480977296829,
          750.6035709381104
        ],
        [
          281.1494916677475,
          750.6035709381104
        ]
      ],
      "group_id": null,
      "description": null,
      "difficult": false,
      "shape_type": "rectangle",
      "flags": {},
      "attributes": {}
    },
    {
      "kie_linking": [],
      "label": "2+",
      "score": 0.5774458050727844,
      "points": [
        [
          274.4006621837616,
          555.8828401565552
        ],
        [
          306.762752532959,
          555.8828401565552
        ],
        [
          306.762752532959,
          583.1117868423462
        ],
        [
          274.4006621837616,
          583.1117868423462
        ]
      ],
      "group_id": null,
      "description": null,
      "difficult": false,
      "shape_type": "rectangle",
      "flags": {},
      "attributes": {}
    },
    {
      "kie_linking": [],
      "label": "2+",
      "score": 0.5754402875900269,
      "points": [
        [
          318.77493619918823,
          998.3737707138062
        ],
        [
          351.1838483810425,
          998.3737707138062
        ],
        [
          351.1838483810425,
          1032.2596216201782
        ],
        [
          318.77493619918823,
          1032.2596216201782
        ]
      ],
      "group_id": null,
      "description": null,
      "difficult": false,
      "shape_type": "rectangle",
      "flags": {},
      "attributes": {}
    },
    {
      "kie_linking": [],
      "label": "2+",
      "score": 0.5659646391868591,
      "points": [
        [
          77.90644824504852,
          527.7040791511536
        ],
        [
          106.5893292427063,
          527.7040791511536
        ],
        [
          106.5893292427063,
          558.295476436615
        ],
        [
          77.90644824504852,
          558.295476436615
        ]
      ],
      "group_id": null,
      "description": null,
      "difficult": false,
      "shape_type": "rectangle",
      "flags": {},
      "attributes": {}
    },
    {
      "kie_linking": [],
      "label": "2+",
      "score": 0.550301730632782,
      "points": [
        [
          126.91312730312347,
          522.1370482444763
        ],
        [
          152.07712769508362,
          522.1370482444763
        ],
        [
          152.07712769508362,
          549.423348903656
        ],
        [
          126.91312730312347,
          549.423348903656
        ]
      ],
      "group_id": null,
      "description": null,
      "difficult": false,
      "shape_type": "rectangle",
      "flags": {},
      "attributes": {}
    },
    {
      "kie_linking": [],
      "label": "2+",
      "score": 0.5439543128013611,
      "points": [
        [
          138.29938769340515,
          736.2984848022461
        ],
        [
          173.2060432434082,
          736.2984848022461
        ],
        [
          173.2060432434082,
          767.7144193649292
        ],
        [
          138.29938769340515,
          767.7144193649292
        ]
      ],
      "group_id": null,
      "description": null,
      "difficult": false,
      "shape_type": "rectangle",
      "flags": {},
      "attributes": {}
    },
    {
      "kie_linking": [],
      "label": "2",
      "score": 0.5352699756622314,
      "points": [
        [
          365.2159857749939,
          581.9420909881592
        ],
        [
          391.06858491897583,
          581.9420909881592
        ],
        [
          391.06858491897583,
          609.4312000274658
        ],
        [
          365.2159857749939,
          609.4312000274658
        ]
      ],
      "group_id": null,
      "description": null,
      "difficult": false,
      "shape_type": "rectangle",
      "flags": {},
      "attributes": {}
    },
    {
      "kie_linking": [],
      "label": "2+",
      "score": 0.5326542258262634,
      "points": [
        [
          5.737771689891815,
          866.4591884613037
        ],
        [
          47.61187255382538,
          866.4591884613037
        ],
        [
          47.61187255382538,
          904.6397876739502
        ],
        [
          5.737771689891815,
          904.6397876739502
        ]
      ],
      "group_id": null,
      "description": null,
      "difficult": false,
      "shape_type": "rectangle",
      "flags": {},
      "attributes": {}
    },
    {
      "kie_linking": [],
      "label": "2",
      "score": 0.5283254981040955,
      "points": [
        [
          24.507755637168884,
          472.79489278793335
        ],
        [
          60.449036955833435,
          472.79489278793335
        ],
        [
          60.449036955833435,
          506.5534710884094
        ],
        [
          24.507755637168884,
          506.5534710884094
        ]
      ],
      "group_id": null,
      "description": null,
      "difficult": false,
      "shape_type": "rectangle",
      "flags": {},
      "attributes": {}
    },
    {
      "kie_linking": [],
      "label": "2+",
      "score": 0.5178016424179077,
      "points": [
        [
          320.66388487815857,
          585.7015109062195
        ],
        [
          349.8555052280426,
          585.7015109062195
        ],
        [
          349.8555052280426,
          617.2725820541382
        ],
        [
          320.66388487815857,
          617.2725820541382
        ]
      ],
      "group_id": null,
      "description": null,
      "difficult": false,
      "shape_type": "rectangle",
      "flags": {},
      "attributes": {}
    },
    {
      "kie_linking": [],
      "label": "2+",
      "score": 0.515724241733551,
      "points": [
        [
          141.52941048145294,
          779.5028781890869
        ],
        [
          172.90221869945526,
          779.5028781890869
        ],
        [
          172.90221869945526,
          807.6837825775146
        ],
        [
          141.52941048145294,
          807.6837825775146
        ]
      ],
      "group_id": null,
      "description": null,
      "difficult": false,
      "shape_type": "rectangle",
      "flags": {},
      "attributes": {}
    },
    {
      "kie_linking": [],
      "label": "2+",
      "score": 0.5122260451316833,
      "points": [
        [
          58.79121333360672,
          824.0042400360107
        ],
        [
          88.19179505109787,
          824.0042400360107
        ],
        [
          88.19179505109787,
          854.3192148208618
        ],
        [
          58.79121333360672,
          854.3192148208618
        ]
      ],
      "group_id": null,
      "description": null,
      "difficult": false,
      "shape_type": "rectangle",
      "flags": {},
      "attributes": {}
    },
    {
      "kie_linking": [],
      "label": "2+",
      "score": 0.505490779876709,
      "points": [
        [
          0.0,
          1026.5970993041992
        ],
        [
          21.34696550667286,
          1026.5970993041992
        ],
        [
          21.34696550667286,
          1061.0245609283447
        ],
        [
          0.0,
          1061.0245609283447
        ]
      ],
      "group_id": null,
      "description": null,
      "difficult": false,
      "shape_type": "rectangle",
      "flags": {},
      "attributes": {}
    },
    {
      "kie_linking": [],
      "label": "2+",
      "score": 0.5044213533401489,
      "points": [
        [
          399.6372389793396,
          1028.6560773849487
        ],
        [
          430.2601218223572,
          1028.6560773849487
        ],
        [
          430.2601218223572,
          1059.2182064056396
        ],
        [
          399.6372389793396,
          1059.2182064056396
        ]
      ],
      "group_id": null,
      "description": null,
      "difficult": false,
      "shape_type": "rectangle",
      "flags": {},
      "attributes": {}
    },
    {
      "kie_linking": [],
      "label": "2+",
      "score": 0.4993267059326172,
      "points": [
        [
          31.45148515701294,
          1009.137544631958
        ],
        [
          64.53768789768219,
          1009.137544631958
        ],
        [
          64.53768789768219,
          1044.5511102676392
        ],
        [
          31.45148515701294,
          1044.5511102676392
        ]
      ],
      "group_id": null,
      "description": null,
      "difficult": false,
      "shape_type": "rectangle",
      "flags": {},
      "attributes": {}
    },
    {
      "kie_linking": [],
      "label": "2+",
      "score": 0.49298974871635437,
      "points": [
        [
          41.8759024143219,
          555.6485462188721
        ],
        [
          73.88420522212982,
          555.6485462188721
        ],
        [
          73.88420522212982,
          585.4303359985352
        ],
        [
          41.8759024143219,
          585.4303359985352
        ]
      ],
      "group_id": null,
      "description": null,
      "difficult": false,
      "shape_type": "rectangle",
      "flags": {},
      "attributes": {}
    },
    {
      "kie_linking": [],
      "label": "3",
      "score": 0.4771508574485779,
      "points": [
        [
          102.1376520395279,
          430.0638544559479
        ],
        [
          142.310488820076,
          430.0638544559479
        ],
        [
          142.310488820076,
          461.1850368976593
        ],
        [
          102.1376520395279,
          461.1850368976593
        ]
      ],
      "group_id": null,
      "description": null,
      "difficult": false,
      "shape_type": "rectangle",
      "flags": {},
      "attributes": {}
    },
    {
      "kie_linking": [],
      "label": "2+",
      "score": 0.47553157806396484,
      "points": [
        [
          154.5973026752472,
          862.5684309005737
        ],
        [
          187.40654706954956,
          862.5684309005737
        ],
        [
          187.40654706954956,
          897.3302602767944
        ],
        [
          154.5973026752472,
          897.3302602767944
        ]
      ],
      "group_id": null,
      "description": null,
      "difficult": false,
      "shape_type": "rectangle",
      "flags": {},
      "attributes": {}
    },
    {
      "kie_linking": [],
      "label": "2+",
      "score": 0.4654921293258667,
      "points": [
        [
          0.00034183263778686523,
          553.0643653869629
        ],
        [
          26.152455657720566,
          553.0643653869629
        ],
        [
          26.152455657720566,
          587.0655155181885
        ],
        [
          0.00034183263778686523,
          587.0655155181885
        ]
      ],
      "group_id": null,
      "description": null,
      "difficult": false,
      "shape_type": "rectangle",
      "flags": {},
      "attributes": {}
    },
    {
      "kie_linking": [],
      "label": "2",
      "score": 0.454074501991272,
      "points": [
        [
          393.81632804870605,
          945.7486176490784
        ],
        [
          425.8808946609497,
          945.7486176490784
        ],
        [
          425.8808946609497,
          979.4731974601746
        ],
        [
          393.81632804870605,
          979.4731974601746
        ]
      ],
      "group_id": null,
      "description": "",
      "difficult": false,
      "shape_type": "rectangle",
      "flags": {},
      "attributes": {}
    },
    {
      "kie_linking": [],
      "label": "2+",
      "score": 0.4517001509666443,
      "points": [
        [
          13.127328343689442,
          772.174060344696
        ],
        [
          45.73041185736656,
          772.174060344696
        ],
        [
          45.73041185736656,
          802.5638318061829
        ],
        [
          13.127328343689442,
          802.5638318061829
        ]
      ],
      "group_id": null,
      "description": null,
      "difficult": false,
      "shape_type": "rectangle",
      "flags": {},
      "attributes": {}
    },
    {
      "kie_linking": [],
      "label": "3",
      "score": 0.44914913177490234,
      "points": [
        [
          235.89545130729675,
          1095.4209065437317
        ],
        [
          264.39165472984314,
          1095.4209065437317
        ],
        [
          264.39165472984314,
          1126.7972254753113
        ],
        [
          235.89545130729675,
          1126.7972254753113
        ]
      ],
      "group_id": null,
      "description": null,
      "difficult": false,
      "shape_type": "rectangle",
      "flags": {},
      "attributes": {}
    },
    {
      "kie_linking": [],
      "label": "2",
      "score": 0.4448871910572052,
      "points": [
        [
          226.49457335472107,
          504.41415309906006
        ],
        [
          258.2724440097809,
          504.41415309906006
        ],
        [
          258.2724440097809,
          532.6763582229614
        ],
        [
          226.49457335472107,
          532.6763582229614
        ]
      ],
      "group_id": null,
      "description": null,
      "difficult": false,
      "shape_type": "rectangle",
      "flags": {},
      "attributes": {}
    },
    {
      "kie_linking": [],
      "label": "2",
      "score": 0.42831480503082275,
      "points": [
        [
          217.35618591308594,
          463.96156787872314
        ],
        [
          244.50538396835327,
          463.96156787872314
        ],
        [
          244.50538396835327,
          491.6159391403198
        ],
        [
          217.35618591308594,
          491.6159391403198
        ]
      ],
      "group_id": null,
      "description": null,
      "difficult": false,
      "shape_type": "rectangle",
      "flags": {},
      "attributes": {}
    },
    {
      "kie_linking": [],
      "label": "2+",
      "score": 0.42290470004081726,
      "points": [
        [
          52.945357859134674,
          771.4527750015259
        ],
        [
          83.8326159119606,
          771.4527750015259
        ],
        [
          83.8326159119606,
          805.3832674026489
        ],
        [
          52.945357859134674,
          805.3832674026489
        ]
      ],
      "group_id": null,
      "description": null,
      "difficult": false,
      "shape_type": "rectangle",
      "flags": {},
      "attributes": {}
    },
    {
      "kie_linking": [],
      "label": "2+",
      "score": 0.4185217022895813,
      "points": [
        [
          110.28995394706726,
          823.4156227111816
        ],
        [
          138.58290553092957,
          823.4156227111816
        ],
        [
          138.58290553092957,
          852.1029567718506
        ],
        [
          110.28995394706726,
          852.1029567718506
        ]
      ],
      "group_id": null,
      "description": null,
      "difficult": false,
      "shape_type": "rectangle",
      "flags": {},
      "attributes": {}
    },
    {
      "kie_linking": [],
      "label": "2",
      "score": 0.4100245237350464,
      "points": [
        [
          319.08291816711426,
          543.623982667923
        ],
        [
          349.08362865448,
          543.623982667923
        ],
        [
          349.08362865448,
          572.9368150234222
        ],
        [
          319.08291816711426,
          572.9368150234222
        ]
      ],
      "group_id": null,
      "description": null,
      "difficult": false,
      "shape_type": "rectangle",
      "flags": {},
      "attributes": {}
    },
    {
      "kie_linking": [],
      "label": "3",
      "score": 0.3923509418964386,
      "points": [
        [
          322.2836172580719,
          14.101885110139847
        ],
        [
          357.285875082016,
          14.101885110139847
        ],
        [
          357.285875082016,
          50.97726568579674
        ],
        [
          322.2836172580719,
          50.97726568579674
        ]
      ],
      "group_id": null,
      "description": null,
      "difficult": false,
      "shape_type": "rectangle",
      "flags": {},
      "attributes": {}
    },
    {
      "kie_linking": [],
      "label": "2+",
      "score": 0.38899627327919006,
      "points": [
        [
          322.9484724998474,
          1092.3881673812866
        ],
        [
          356.9584918022156,
          1092.3881673812866
        ],
        [
          356.9584918022156,
          1132.2154760360718
        ],
        [
          322.9484724998474,
          1132.2154760360718
        ]
      ],
      "group_id": null,
      "description": null,
      "difficult": false,
      "shape_type": "rectangle",
      "flags": {},
      "attributes": {}
    },
    {
      "kie_linking": [],
      "label": "2+",
      "score": 0.38771456480026245,
      "points": [
        [
          219.07702684402466,
          1002.9468631744385
        ],
        [
          255.4197120666504,
          1002.9468631744385
        ],
        [
          255.4197120666504,
          1037.3441696166992
        ],
        [
          219.07702684402466,
          1037.3441696166992
        ]
      ],
      "group_id": null,
      "description": null,
      "difficult": false,
      "shape_type": "rectangle",
      "flags": {},
      "attributes": {}
    },
    {
      "kie_linking": [],
      "label": "2",
      "score": 0.3833601474761963,
      "points": [
        [
          415.0354504585266,
          986.8825030326843
        ],
        [
          445.59528827667236,
          986.8825030326843
        ],
        [
          445.59528827667236,
          1018.6965155601501
        ],
        [
          415.0354504585266,
          1018.6965155601501
        ]
      ],
      "group_id": null,
      "description": "",
      "difficult": false,
      "shape_type": "rectangle",
      "flags": {},
      "attributes": {}
    },
    {
      "kie_linking": [],
      "label": "2",
      "score": 0.3811658024787903,
      "points": [
        [
          79.94916617870331,
          466.6691780090332
        ],
        [
          111.99444234371185,
          466.6691780090332
        ],
        [
          111.99444234371185,
          499.8647117614746
        ],
        [
          79.94916617870331,
          499.8647117614746
        ]
      ],
      "group_id": null,
      "description": null,
      "difficult": false,
      "shape_type": "rectangle",
      "flags": {},
      "attributes": {}
    },
    {
      "kie_linking": [],
      "label": "2+",
      "score": 0.3716368079185486,
      "points": [
        [
          158.24737310409546,
          0.32780133187770844
        ],
        [
          184.1672670841217,
          0.32780133187770844
        ],
        [
          184.1672670841217,
          18.3442360162735
        ],
        [
          158.24737310409546,
          18.3442360162735
        ]
      ],
      "group_id": null,
      "description": null,
      "difficult": false,
      "shape_type": "rectangle",
      "flags": {},
      "attributes": {}
    },
    {
      "kie_linking": [],
      "label": "3",
      "score": 0.36798596382141113,
      "points": [
        [
          36.7960199713707,
          400.4691672325134
        ],
        [
          76.22003078460693,
          400.4691672325134
        ],
        [
          76.22003078460693,
          439.37171697616577
        ],
        [
          36.7960199713707,
          439.37171697616577
        ]
      ],
      "group_id": null,
      "description": null,
      "difficult": false,
      "shape_type": "rectangle",
      "flags": {},
      "attributes": {}
    },
    {
      "kie_linking": [],
      "label": "2",
      "score": 0.363593727350235,
      "points": [
        [
          184.01630640029907,
          1054.8890900611877
        ],
        [
          212.24968671798706,
          1054.8890900611877
        ],
        [
          212.24968671798706,
          1090.3291153907776
        ],
        [
          184.01630640029907,
          1090.3291153907776
        ]
      ],
      "group_id": null,
      "description": null,
      "difficult": false,
      "shape_type": "rectangle",
      "flags": {},
      "attributes": {}
    },
    {
      "kie_linking": [],
      "label": "3",
      "score": 0.3605974316596985,
      "points": [
        [
          170.6422060728073,
          30.14141619205475
        ],
        [
          209.84191000461578,
          30.14141619205475
        ],
        [
          209.84191000461578,
          67.78204917907715
        ],
        [
          170.6422060728073,
          67.78204917907715
        ]
      ],
      "group_id": null,
      "description": null,
      "difficult": false,
      "shape_type": "rectangle",
      "flags": {},
      "attributes": {}
    },
    {
      "kie_linking": [],
      "label": "2+",
      "score": 0.3579137325286865,
      "points": [
        [
          103.8309246301651,
          704.7994017601013
        ],
        [
          130.76013028621674,
          704.7994017601013
        ],
        [
          130.76013028621674,
          732.6930928230286
        ],
        [
          103.8309246301651,
          732.6930928230286
        ]
      ],
      "group_id": null,
      "description": null,
      "difficult": false,
      "shape_type": "rectangle",
      "flags": {},
      "attributes": {}
    },
    {
      "kie_linking": [],
      "label": "2+",
      "score": 0.34919166564941406,
      "points": [
        [
          148.6980104446411,
          655.3763890266418
        ],
        [
          173.17766189575195,
          655.3763890266418
        ],
        [
          173.17766189575195,
          681.7728161811829
        ],
        [
          148.6980104446411,
          681.7728161811829
        ]
      ],
      "group_id": null,
      "description": null,
      "difficult": false,
      "shape_type": "rectangle",
      "flags": {},
      "attributes": {}
    },
    {
      "kie_linking": [],
      "label": "2",
      "score": 0.34897375106811523,
      "points": [
        [
          372.08715438842773,
          712.8506135940552
        ],
        [
          397.8789258003235,
          712.8506135940552
        ],
        [
          397.8789258003235,
          740.447039604187
        ],
        [
          372.08715438842773,
          740.447039604187
        ]
      ],
      "group_id": null,
      "description": null,
      "difficult": false,
      "shape_type": "rectangle",
      "flags": {},
      "attributes": {}
    },
    {
      "kie_linking": [],
      "label": "2",
      "score": 0.3458900451660156,
      "points": [
        [
          24.58019644021988,
          528.8547801971436
        ],
        [
          56.372045278549194,
          528.8547801971436
        ],
        [
          56.372045278549194,
          557.1107769012451
        ],
        [
          24.58019644021988,
          557.1107769012451
        ]
      ],
      "group_id": null,
      "description": null,
      "difficult": false,
      "shape_type": "rectangle",
      "flags": {},
      "attributes": {}
    },
    {
      "kie_linking": [],
      "label": "3",
      "score": 0.3230826258659363,
      "points": [
        [
          88.17578434944153,
          15.456526279449463
        ],
        [
          129.36508357524872,
          15.456526279449463
        ],
        [
          129.36508357524872,
          55.239752382040024
        ],
        [
          88.17578434944153,
          55.239752382040024
        ]
      ],
      "group_id": null,
      "description": null,
      "difficult": false,
      "shape_type": "rectangle",
      "flags": {},
      "attributes": {}
    },
    {
      "kie_linking": [],
      "label": "2+",
      "score": 0.32210981845855713,
      "points": [
        [
          196.39578461647034,
          1142.9125833511353
        ],
        [
          222.41335034370422,
          1142.9125833511353
        ],
        [
          222.41335034370422,
          1170.7780408859253
        ],
        [
          196.39578461647034,
          1170.7780408859253
        ]
      ],
      "group_id": null,
      "description": null,
      "difficult": false,
      "shape_type": "rectangle",
      "flags": {},
      "attributes": {}
    },
    {
      "kie_linking": [],
      "label": "2+",
      "score": 0.3175963759422302,
      "points": [
        [
          79.24129545688629,
          560.0707149505615
        ],
        [
          110.5118864774704,
          560.0707149505615
        ],
        [
          110.5118864774704,
          585.7712078094482
        ],
        [
          79.24129545688629,
          585.7712078094482
        ]
      ],
      "group_id": null,
      "description": null,
      "difficult": false,
      "shape_type": "rectangle",
      "flags": {},
      "attributes": {}
    },
    {
      "kie_linking": [],
      "label": "2+",
      "score": 0.3117126226425171,
      "points": [
        [
          0.015715062618255615,
          1069.6215963363647
        ],
        [
          22.97300562262535,
          1069.6215963363647
        ],
        [
          22.97300562262535,
          1096.146330833435
        ],
        [
          0.015715062618255615,
          1096.146330833435
        ]
      ],
      "group_id": null,
      "description": null,
      "difficult": false,
      "shape_type": "rectangle",
      "flags": {},
      "attributes": {}
    },
    {
      "kie_linking": [],
      "label": "2+",
      "score": 0.31036606431007385,
      "points": [
        [
          378.3600974082947,
          1080.1422810554504
        ],
        [
          420.02044200897217,
          1080.1422810554504
        ],
        [
          420.02044200897217,
          1110.307810306549
        ],
        [
          378.3600974082947,
          1110.307810306549
        ]
      ],
      "group_id": null,
      "description": null,
      "difficult": false,
      "shape_type": "rectangle",
      "flags": {},
      "attributes": {}
    },
    {
      "kie_linking": [],
      "label": "2+",
      "score": 0.3088284730911255,
      "points": [
        [
          69.68367800116539,
          915.9062957763672
        ],
        [
          104.05115723609924,
          915.9062957763672
        ],
        [
          104.05115723609924,
          950.3689384460449
        ],
        [
          69.68367800116539,
          950.3689384460449
        ]
      ],
      "group_id": null,
      "description": null,
      "difficult": false,
      "shape_type": "rectangle",
      "flags": {},
      "attributes": {}
    },
    {
      "kie_linking": [],
      "label": "3",
      "score": 0.307888388633728,
      "points": [
        [
          207.32472836971283,
          69.42349255084991
        ],
        [
          243.39428007602692,
          69.42349255084991
        ],
        [
          243.39428007602692,
          113.69359076023102
        ],
        [
          207.32472836971283,
          113.69359076023102
        ]
      ],
      "group_id": null,
      "description": null,
      "difficult": false,
      "shape_type": "rectangle",
      "flags": {},
      "attributes": {}
    },
    {
      "kie_linking": [],
      "label": "2",
      "score": 0.2988527715206146,
      "points": [
        [
          81.27571702003479,
          1058.1247854232788
        ],
        [
          113.20920467376709,
          1058.1247854232788
        ],
        [
          113.20920467376709,
          1092.6536512374878
        ],
        [
          81.27571702003479,
          1092.6536512374878
        ]
      ],
      "group_id": null,
      "description": null,
      "difficult": false,
      "shape_type": "rectangle",
      "flags": {},
      "attributes": {}
    },
    {
      "kie_linking": [],
      "label": "2",
      "score": 0.2937963008880615,
      "points": [
        [
          124.78291869163513,
          469.7338831424713
        ],
        [
          151.99235320091248,
          469.7338831424713
        ],
        [
          151.99235320091248,
          496.2668216228485
        ],
        [
          124.78291869163513,
          496.2668216228485
        ]
      ],
      "group_id": null,
      "description": null,
      "difficult": false,
      "shape_type": "rectangle",
      "flags": {},
      "attributes": {}
    },
    {
      "kie_linking": [],
      "label": "2+",
      "score": 0.2832620143890381,
      "points": [
        [
          79.37141358852386,
          466.65107011795044
        ],
        [
          111.80552899837494,
          466.65107011795044
        ],
        [
          111.80552899837494,
          500.14697313308716
        ],
        [
          79.37141358852386,
          500.14697313308716
        ]
      ],
      "group_id": null,
      "description": null,
      "difficult": false,
      "shape_type": "rectangle",
      "flags": {},
      "attributes": {}
    },
    {
      "kie_linking": [],
      "label": "2",
      "score": 0.28145134449005127,
      "points": [
        [
          275.82148492336273,
          1098.5389375686646
        ],
        [
          303.3063071966171,
          1098.5389375686646
        ],
        [
          303.3063071966171,
          1128.755316734314
        ],
        [
          275.82148492336273,
          1128.755316734314
        ]
      ],
      "group_id": null,
      "description": null,
      "difficult": false,
      "shape_type": "rectangle",
      "flags": {},
      "attributes": {}
    },
    {
      "kie_linking": [],
      "label": "2+",
      "score": 0.28097087144851685,
      "points": [
        [
          237.72704601287842,
          1183.6083316802979
        ],
        [
          266.9976019859314,
          1183.6083316802979
        ],
        [
          266.9976019859314,
          1215.451316833496
        ],
        [
          237.72704601287842,
          1215.451316833496
        ]
      ],
      "group_id": null,
      "description": null,
      "difficult": false,
      "shape_type": "rectangle",
      "flags": {},
      "attributes": {}
    },
    {
      "kie_linking": [],
      "label": "2+",
      "score": 0.2773743271827698,
      "points": [
        [
          427.9153347015381,
          1075.518856048584
        ],
        [
          456.1212205886841,
          1075.518856048584
        ],
        [
          456.1212205886841,
          1109.3092155456543
        ],
        [
          427.9153347015381,
          1109.3092155456543
        ]
      ],
      "group_id": null,
      "description": null,
      "difficult": false,
      "shape_type": "rectangle",
      "flags": {},
      "attributes": {}
    },
    {
      "kie_linking": [],
      "label": "2+",
      "score": 0.2772009074687958,
      "points": [
        [
          179.26765978336334,
          1108.1748485565186
        ],
        [
          210.66478431224823,
          1108.1748485565186
        ],
        [
          210.66478431224823,
          1138.8033485412598
        ],
        [
          179.26765978336334,
          1138.8033485412598
        ]
      ],
      "group_id": null,
      "description": null,
      "difficult": false,
      "shape_type": "rectangle",
      "flags": {},
      "attributes": {}
    },
    {
      "kie_linking": [],
      "label": "3+",
      "score": 0.2750672698020935,
      "points": [
        [
          79.56612884998322,
          80.82331538200378
        ],
        [
          112.7056759595871,
          80.82331538200378
        ],
        [
          112.7056759595871,
          112.33274579048157
        ],
        [
          79.56612884998322,
          112.33274579048157
        ]
      ],
      "group_id": null,
      "description": null,
      "difficult": false,
      "shape_type": "rectangle",
      "flags": {},
      "attributes": {}
    },
    {
      "kie_linking": [],
      "label": "3",
      "score": 0.25884824991226196,
      "points": [
        [
          365.895733833313,
          84.46786105632782
        ],
        [
          401.7061948776245,
          84.46786105632782
        ],
        [
          401.7061948776245,
          121.07588231563568
        ],
        [
          365.895733833313,
          121.07588231563568
        ]
      ],
      "group_id": null,
      "description": null,
      "difficult": false,
      "shape_type": "rectangle",
      "flags": {},
      "attributes": {}
    },
    {
      "kie_linking": [],
      "label": "2",
      "score": 0.25362569093704224,
      "points": [
        [
          0.0,
          474.4504714012146
        ],
        [
          19.794414788484573,
          474.4504714012146
        ],
        [
          19.794414788484573,
          505.3024744987488
        ],
        [
          0.0,
          505.3024744987488
        ]
      ],
      "group_id": null,
      "description": null,
      "difficult": false,
      "shape_type": "rectangle",
      "flags": {},
      "attributes": {}
    }
  ],
  "imagePath": "20240926101830113.bmp",
  "imageData": null,
  "imageHeight": 1240,
  "imageWidth": 1240,
  "description": ""
}