{
  "version": "3.1.1",
  "flags": {},
  "shapes": [
    {
      "kie_linking": [],
      "label": "2",
      "score": 0.6924679279327393,
      "points": [
        [454.2911410331726, 230.53473949432373],
        [480.6523871421814, 230.53473949432373],
        [480.6523871421814, 258.81564378738403],
        [454.2911410331726, 258.81564378738403]
      ],
      "group_id": null,
      "description": null,
      "difficult": false,
      "shape_type": "rectangle",
      "flags": {},
      "attributes": {}
    },
    {
      "kie_linking": [],
      "label": "2",
      "score": 0.6613466143608093,
      "points": [
        [497.61467695236206, 224.0624064207077],
        [528.4180474281311, 224.0624064207077],
        [528.4180474281311, 255.18573224544525],
        [497.61467695236206, 255.18573224544525]
      ],
      "group_id": null,
      "description": null,
      "difficult": false,
      "shape_type": "rectangle",
      "flags": {},
      "attributes": {}
    },
    {
      "kie_linking": [],
      "label": "2",
      "score": 0.6292445659637451,
      "points": [
        [522.4175357818604, 168.8872742652893],
        [553.6071586608887, 168.8872742652893],
        [553.6071586608887, 204.66126084327698],
        [522.4175357818604, 204.66126084327698]
      ],
      "group_id": null,
      "description": null,
      "difficult": false,
      "shape_type": "rectangle",
      "flags": {},
      "attributes": {}
    },
    {
      "kie_linking": [],
      "label": "3",
      "score": 0.6087357997894287,
      "points": [
        [357.7500653266907, 694.4515180587769],
        [387.13067293167114, 694.4515180587769],
        [387.13067293167114, 720.2525281906128],
        [357.7500653266907, 720.2525281906128]
      ],
      "group_id": null,
      "description": null,
      "difficult": false,
      "shape_type": "rectangle",
      "flags": {},
      "attributes": {}
    },
    {
      "kie_linking": [],
      "label": "2",
      "score": 0.5865769386291504,
      "points": [
        [309.89591658115387, 651.8693709373474],
        [344.7400999069214, 651.8693709373474],
        [344.7400999069214, 683.7003827095032],
        [309.89591658115387, 683.7003827095032]
      ],
      "group_id": null,
      "description": null,
      "difficult": false,
      "shape_type": "rectangle",
      "flags": {},
      "attributes": {}
    },
    {
      "kie_linking": [],
      "label": "3",
      "score": 0.5790398716926575,
      "points": [
        [403.70744943618774, 51.518816351890564],
        [447.66801357269287, 51.518816351890564],
        [447.66801357269287, 98.55395257472992],
        [403.70744943618774, 98.55395257472992]
      ],
      "group_id": null,
      "description": null,
      "difficult": false,
      "shape_type": "rectangle",
      "flags": {},
      "attributes": {}
    },
    {
      "kie_linking": [],
      "label": "2",
      "score": 0.5603929162025452,
      "points": [
        [589.2086029052734, 212.63187408447266],
        [616.0427236557007, 212.63187408447266],
        [616.0427236557007, 243.02393674850464],
        [589.2086029052734, 243.02393674850464]
      ],
      "group_id": null,
      "description": "",
      "difficult": false,
      "shape_type": "rectangle",
      "flags": {},
      "attributes": {}
    },
    {
      "kie_linking": [],
      "label": "2",
      "score": 0.554871141910553,
      "points": [
        [507.1783781051636, 314.0190649032593],
        [533.2462763786316, 314.0190649032593],
        [533.2462763786316, 341.5081739425659],
        [507.1783781051636, 341.5081739425659]
      ],
      "group_id": null,
      "description": null,
      "difficult": false,
      "shape_type": "rectangle",
      "flags": {},
      "attributes": {}
    },
    {
      "kie_linking": [],
      "label": "2",
      "score": 0.5404495000839233,
      "points": [
        [371.6842722892761, 404.1547882556915],
        [394.2730164527893, 404.1547882556915],
        [394.2730164527893, 431.8600833415985],
        [371.6842722892761, 431.8600833415985]
      ],
      "group_id": null,
      "description": null,
      "difficult": false,
      "shape_type": "rectangle",
      "flags": {},
      "attributes": {}
    },
    {
      "kie_linking": [],
      "label": "2",
      "score": 0.5239277482032776,
      "points": [
        [671.3761520385742, 196.8053925037384],
        [696.9929790496826, 196.8053925037384],
        [696.9929790496826, 226.6429102420807],
        [671.3761520385742, 226.6429102420807]
      ],
      "group_id": null,
      "description": null,
      "difficult": false,
      "shape_type": "rectangle",
      "flags": {},
      "attributes": {}
    },
    {
      "kie_linking": [],
      "label": "2",
      "score": 0.5176563858985901,
      "points": [
        [624.2221689224243, 248.17681431770325],
        [650.1671552658081, 248.17681431770325],
        [650.1671552658081, 277.2356188297272],
        [624.2221689224243, 277.2356188297272]
      ],
      "group_id": null,
      "description": null,
      "difficult": false,
      "shape_type": "rectangle",
      "flags": {},
      "attributes": {}
    },
    {
      "kie_linking": [],
      "label": "2",
      "score": 0.5036539435386658,
      "points": [
        [274.3143355846405, 344.0345573425293],
        [304.10211205482483, 344.0345573425293],
        [304.10211205482483, 374.18293952941895],
        [274.3143355846405, 374.18293952941895]
      ],
      "group_id": null,
      "description": "",
      "difficult": false,
      "shape_type": "rectangle",
      "flags": {},
      "attributes": {}
    },
    {
      "kie_linking": [],
      "label": "3",
      "score": 0.5000119209289551,
      "points": [
        [702.4049472808838, 557.9422616958618],
        [730.3112030029297, 557.9422616958618],
        [730.3112030029297, 585.3224277496338],
        [702.4049472808838, 585.3224277496338]
      ],
      "group_id": null,
      "description": null,
      "difficult": false,
      "shape_type": "rectangle",
      "flags": {},
      "attributes": {}
    },
    {
      "kie_linking": [],
      "label": "2",
      "score": 0.4997727870941162,
      "points": [
        [441.2374210357666, 185.97526609897614],
        [469.02660369873047, 185.97526609897614],
        [469.02660369873047, 219.9807769060135],
        [441.2374210357666, 219.9807769060135]
      ],
      "group_id": null,
      "description": null,
      "difficult": false,
      "shape_type": "rectangle",
      "flags": {},
      "attributes": {}
    },
    {
      "kie_linking": [],
      "label": "2",
      "score": 0.489940345287323,
      "points": [
        [412.4971675872803, 242.49295055866241],
        [444.01029348373413, 242.49295055866241],
        [444.01029348373413, 274.3347901105881],
        [412.4971675872803, 274.3347901105881]
      ],
      "group_id": null,
      "description": null,
      "difficult": false,
      "shape_type": "rectangle",
      "flags": {},
      "attributes": {}
    },
    {
      "kie_linking": [],
      "label": "2",
      "score": 0.47929826378822327,
      "points": [
        [479.22629833221436, 181.77480816841125],
        [506.0349941253662, 181.77480816841125],
        [506.0349941253662, 213.9587390422821],
        [479.22629833221436, 213.9587390422821]
      ],
      "group_id": null,
      "description": null,
      "difficult": false,
      "shape_type": "rectangle",
      "flags": {},
      "attributes": {}
    },
    {
      "kie_linking": [],
      "label": "2",
      "score": 0.47521334886550903,
      "points": [
        [538.148045539856, 345.8283472061157],
        [567.9936933517456, 345.8283472061157],
        [567.9936933517456, 372.87022829055786],
        [538.148045539856, 372.87022829055786]
      ],
      "group_id": null,
      "description": null,
      "difficult": false,
      "shape_type": "rectangle",
      "flags": {},
      "attributes": {}
    },
    {
      "kie_linking": [],
      "label": "2",
      "score": 0.458477258682251,
      "points": [
        [627.7790760993958, 204.0796834230423],
        [655.0427603721619, 204.0796834230423],
        [655.0427603721619, 235.09410321712494],
        [627.7790760993958, 235.09410321712494]
      ],
      "group_id": null,
      "description": "",
      "difficult": false,
      "shape_type": "rectangle",
      "flags": {},
      "attributes": {}
    },
    {
      "kie_linking": [],
      "label": "3",
      "score": 0.44159799814224243,
      "points": [
        [342.24161744117737, 33.18599708378315],
        [384.5890271663666, 33.18599708378315],
        [384.5890271663666, 79.50437724590302],
        [342.24161744117737, 79.50437724590302]
      ],
      "group_id": null,
      "description": null,
      "difficult": false,
      "shape_type": "rectangle",
      "flags": {},
      "attributes": {}
    },
    {
      "kie_linking": [],
      "label": "2+",
      "score": 0.4306287467479706,
      "points": [
        [725.0995302200317, 598.7520527839661],
        [748.1772613525391, 598.7520527839661],
        [748.1772613525391, 623.8117480278015],
        [725.0995302200317, 623.8117480278015]
      ],
      "group_id": null,
      "description": null,
      "difficult": false,
      "shape_type": "rectangle",
      "flags": {},
      "attributes": {}
    },
    {
      "kie_linking": [],
      "label": "2",
      "score": 0.4206656217575073,
      "points": [
        [584.2457842826843, 254.36721861362457],
        [611.4258027076721, 254.36721861362457],
        [611.4258027076721, 283.5923570394516],
        [584.2457842826843, 283.5923570394516]
      ],
      "group_id": null,
      "description": "",
      "difficult": false,
      "shape_type": "rectangle",
      "flags": {},
      "attributes": {}
    },
    {
      "kie_linking": [],
      "label": "2",
      "score": 0.4128918945789337,
      "points": [
        [545.4408693313599, 302.4559015035629],
        [573.3143091201782, 302.4559015035629],
        [573.3143091201782, 330.31572341918945],
        [545.4408693313599, 330.31572341918945]
      ],
      "group_id": null,
      "description": null,
      "difficult": false,
      "shape_type": "rectangle",
      "flags": {},
      "attributes": {}
    },
    {
      "kie_linking": [],
      "label": "2",
      "score": 0.40436410903930664,
      "points": [
        [540.3771638870239, 257.1077370643616],
        [568.9545202255249, 257.1077370643616],
        [568.9545202255249, 288.23461055755615],
        [540.3771638870239, 288.23461055755615]
      ],
      "group_id": null,
      "description": null,
      "difficult": false,
      "shape_type": "rectangle",
      "flags": {},
      "attributes": {}
    },
    {
      "kie_linking": [],
      "label": "2",
      "score": 0.40370792150497437,
      "points": [
        [626.5368008613586, 164.92120265960693],
        [653.5585045814514, 164.92120265960693],
        [653.5585045814514, 193.44608306884766],
        [626.5368008613586, 193.44608306884766]
      ],
      "group_id": null,
      "description": null,
      "difficult": false,
      "shape_type": "rectangle",
      "flags": {},
      "attributes": {}
    },
    {
      "kie_linking": [],
      "label": "2",
      "score": 0.39975422620773315,
      "points": [
        [259.4370770454407, 644.0677523612976],
        [289.4233751296997, 644.0677523612976],
        [289.4233751296997, 671.2403798103333],
        [259.4370770454407, 671.2403798103333]
      ],
      "group_id": null,
      "description": null,
      "difficult": false,
      "shape_type": "rectangle",
      "flags": {},
      "attributes": {}
    },
    {
      "kie_linking": [],
      "label": "2",
      "score": 0.3922909200191498,
      "points": [
        [500.25185108184814, 355.53295731544495],
        [522.9442167282104, 355.53295731544495],
        [522.9442167282104, 383.75192523002625],
        [500.25185108184814, 383.75192523002625]
      ],
      "group_id": null,
      "description": "",
      "difficult": false,
      "shape_type": "rectangle",
      "flags": {},
      "attributes": {}
    },
    {
      "kie_linking": [],
      "label": "2",
      "score": 0.3715277910232544,
      "points": [
        [539.8300099372864, 215.52564442157745],
        [569.0585112571716, 215.52564442157745],
        [569.0585112571716, 245.22639214992523],
        [539.8300099372864, 245.22639214992523]
      ],
      "group_id": null,
      "description": null,
      "difficult": false,
      "shape_type": "rectangle",
      "flags": {},
      "attributes": {}
    },
    {
      "kie_linking": [],
      "label": "2",
      "score": 0.37085089087486267,
      "points": [
        [589.3383145332336, 341.6777229309082],
        [614.6320080757141, 341.6777229309082],
        [614.6320080757141, 368.95079374313354],
        [589.3383145332336, 368.95079374313354]
      ],
      "group_id": null,
      "description": null,
      "difficult": false,
      "shape_type": "rectangle",
      "flags": {},
      "attributes": {}
    },
    {
      "kie_linking": [],
      "label": "3",
      "score": 0.3547213673591614,
      "points": [
        [609.1103208065033, 31.062414944171906],
        [649.0345621109009, 31.062414944171906],
        [649.0345621109009, 73.25046598911285],
        [609.1103208065033, 73.25046598911285]
      ],
      "group_id": null,
      "description": null,
      "difficult": false,
      "shape_type": "rectangle",
      "flags": {},
      "attributes": {}
    },
    {
      "kie_linking": [],
      "label": "2",
      "score": 0.3546451926231384,
      "points": [
        [584.0904259681702, 177.1836817264557],
        [613.296902179718, 177.1836817264557],
        [613.296902179718, 206.95475459098816],
        [584.0904259681702, 206.95475459098816]
      ],
      "group_id": null,
      "description": null,
      "difficult": false,
      "shape_type": "rectangle",
      "flags": {},
      "attributes": {}
    },
    {
      "kie_linking": [],
      "label": "2",
      "score": 0.3456052839756012,
      "points": [
        [470.76584815979004, 491.1462426185608],
        [497.3309373855591, 491.1462426185608],
        [497.3309373855591, 518.5092616081238],
        [470.76584815979004, 518.5092616081238]
      ],
      "group_id": null,
      "description": "",
      "difficult": false,
      "shape_type": "rectangle",
      "flags": {},
      "attributes": {}
    },
    {
      "kie_linking": [],
      "label": "2",
      "score": 0.3193472921848297,
      "points": [
        [227.82799780368805, 346.7931652069092],
        [259.96377646923065, 346.7931652069092],
        [259.96377646923065, 379.36453104019165],
        [227.82799780368805, 379.36453104019165]
      ],
      "group_id": null,
      "description": "",
      "difficult": false,
      "shape_type": "rectangle",
      "flags": {},
      "attributes": {}
    },
    {
      "kie_linking": [],
      "label": "2+",
      "score": 0.3115260601043701,
      "points": [
        [628.0802583694458, 612.4740278720856],
        [657.3848867416382, 612.4740278720856],
        [657.3848867416382, 641.5368604660034],
        [628.0802583694458, 641.5368604660034]
      ],
      "group_id": null,
      "description": null,
      "difficult": false,
      "shape_type": "rectangle",
      "flags": {},
      "attributes": {}
    },
    {
      "kie_linking": [],
      "label": "2",
      "score": 0.2988305687904358,
      "points": [
        [334.402859210968, 399.5894193649292],
        [362.82249212265015, 399.5894193649292],
        [362.82249212265015, 432.7250862121582],
        [334.402859210968, 432.7250862121582]
      ],
      "group_id": null,
      "description": null,
      "difficult": false,
      "shape_type": "rectangle",
      "flags": {},
      "attributes": {}
    },
    {
      "kie_linking": [],
      "label": "2",
      "score": 0.2851228713989258,
      "points": [
        [201.9366329908371, 114.98379647731781],
        [239.21021163463593, 114.98379647731781],
        [239.21021163463593, 159.35722053050995],
        [201.9366329908371, 159.35722053050995]
      ],
      "group_id": null,
      "description": null,
      "difficult": false,
      "shape_type": "rectangle",
      "flags": {},
      "attributes": {}
    },
    {
      "kie_linking": [],
      "label": "3",
      "score": 0.2746644616127014,
      "points": [
        [750.9131050109863, 0.30436038970947266],
        [796.6259956359863, 0.30436038970947266],
        [796.6259956359863, 47.97129571437836],
        [750.9131050109863, 47.97129571437836]
      ],
      "group_id": null,
      "description": null,
      "difficult": false,
      "shape_type": "rectangle",
      "flags": {},
      "attributes": {}
    },
    {
      "kie_linking": [],
      "label": "2",
      "score": 0.2617218494415283,
      "points": [
        [303.30155849456787, 184.81965005397797],
        [340.78762769699097, 184.81965005397797],
        [340.78762769699097, 223.95911753177643],
        [303.30155849456787, 223.95911753177643]
      ],
      "group_id": null,
      "description": null,
      "difficult": false,
      "shape_type": "rectangle",
      "flags": {},
      "attributes": {}
    },
    {
      "kie_linking": [],
      "label": "2",
      "score": 0.2608245313167572,
      "points": [
        [180.25747776031494, 314.76226449012756],
        [214.16387557983398, 314.76226449012756],
        [214.16387557983398, 353.9954125881195],
        [180.25747776031494, 353.9954125881195]
      ],
      "group_id": null,
      "description": null,
      "difficult": false,
      "shape_type": "rectangle",
      "flags": {},
      "attributes": {}
    },
    {
      "kie_linking": [],
      "label": "2",
      "score": 0.25223609805107117,
      "points": [
        [512.4339532852173, 483.77928733825684],
        [543.3271980285645, 483.77928733825684],
        [543.3271980285645, 511.5371322631836],
        [512.4339532852173, 511.5371322631836]
      ],
      "group_id": null,
      "description": null,
      "difficult": false,
      "shape_type": "rectangle",
      "flags": {},
      "attributes": {}
    },
    {
      "kie_linking": [],
      "label": "3",
      "score": null,
      "points": [
        [391.875, 684.5833333333333],
        [422.08333333333326, 684.5833333333333],
        [422.08333333333326, 710.6249999999999],
        [391.875, 710.6249999999999]
      ],
      "group_id": null,
      "description": "",
      "difficult": false,
      "shape_type": "rectangle",
      "flags": {},
      "attributes": {}
    },
    {
      "kie_linking": [],
      "label": "2+",
      "score": null,
      "points": [
        [580.4166666666667, 624.1666666666666],
        [614.7916666666667, 624.1666666666666],
        [614.7916666666667, 649.1666666666666],
        [580.4166666666667, 649.1666666666666]
      ],
      "group_id": null,
      "description": "",
      "difficult": false,
      "shape_type": "rectangle",
      "flags": {},
      "attributes": {}
    },
    {
      "kie_linking": [],
      "label": "2+",
      "score": null,
      "points": [
        [533.5416666666667, 621.0416666666666],
        [559.5833333333333, 621.0416666666666],
        [559.5833333333333, 644.9999999999999],
        [533.5416666666667, 644.9999999999999]
      ],
      "group_id": null,
      "description": "",
      "difficult": false,
      "shape_type": "rectangle",
      "flags": {},
      "attributes": {}
    },
    {
      "kie_linking": [],
      "label": "3",
      "score": null,
      "points": [
        [661.6666666666667, 137.70833333333326],
        [691.875, 137.70833333333326],
        [691.875, 175.20833333333326],
        [661.6666666666667, 175.20833333333326]
      ],
      "group_id": null,
      "description": "",
      "difficult": false,
      "shape_type": "rectangle",
      "flags": {},
      "attributes": {}
    },
    {
      "kie_linking": [],
      "label": "2",
      "score": null,
      "points": [
        [464.79166666666663, 444.99999999999994],
        [495.0, 444.99999999999994],
        [495.0, 476.24999999999994],
        [464.79166666666663, 476.24999999999994]
      ],
      "group_id": null,
      "description": "",
      "difficult": false,
      "shape_type": "rectangle",
      "flags": {},
      "attributes": {}
    },
    {
      "kie_linking": [],
      "label": "2",
      "score": null,
      "points": [
        [457.5, 401.24999999999994],
        [493.95833333333326, 401.24999999999994],
        [493.95833333333326, 426.24999999999994],
        [457.5, 426.24999999999994]
      ],
      "group_id": null,
      "description": "",
      "difficult": false,
      "shape_type": "rectangle",
      "flags": {},
      "attributes": {}
    },
    {
      "kie_linking": [],
      "label": "2",
      "score": null,
      "points": [
        [248.125, 113.74999999999993],
        [279.375, 113.74999999999993],
        [279.375, 154.37499999999994],
        [248.125, 154.37499999999994]
      ],
      "group_id": null,
      "description": "",
      "difficult": false,
      "shape_type": "rectangle",
      "flags": {},
      "attributes": {}
    },
    {
      "kie_linking": [],
      "label": "2",
      "score": null,
      "points": [
        [385.625, 100.20833333333327],
        [422.08333333333326, 100.20833333333327],
        [422.08333333333326, 134.58333333333326],
        [385.625, 134.58333333333326]
      ],
      "group_id": null,
      "description": "",
      "difficult": false,
      "shape_type": "rectangle",
      "flags": {},
      "attributes": {}
    },
    {
      "kie_linking": [],
      "label": "2",
      "score": null,
      "points": [
        [388.75, 163.74999999999994],
        [416.875, 163.74999999999994],
        [416.875, 194.99999999999994],
        [388.75, 194.99999999999994]
      ],
      "group_id": null,
      "description": "",
      "difficult": false,
      "shape_type": "rectangle",
      "flags": {},
      "attributes": {}
    },
    {
      "kie_linking": [],
      "label": "2",
      "score": null,
      "points": [
        [325.20833333333326, 453.3333333333333],
        [353.33333333333326, 453.3333333333333],
        [353.33333333333326, 483.54166666666663],
        [325.20833333333326, 483.54166666666663]
      ],
      "group_id": null,
      "description": "",
      "difficult": false,
      "shape_type": "rectangle",
      "flags": {},
      "attributes": {}
    },
    {
      "kie_linking": [],
      "label": "2",
      "score": null,
      "points": [
        [162.70833333333326, 256.4583333333333],
        [196.04166666666663, 256.4583333333333],
        [196.04166666666663, 289.79166666666663],
        [162.70833333333326, 289.79166666666663]
      ],
      "group_id": null,
      "description": "",
      "difficult": false,
      "shape_type": "rectangle",
      "flags": {},
      "attributes": {}
    },
    {
      "kie_linking": [],
      "label": "2",
      "score": null,
      "points": [
        [216.875, 211.66666666666663],
        [250.20833333333326, 211.66666666666663],
        [250.20833333333326, 244.99999999999994],
        [216.875, 244.99999999999994]
      ],
      "group_id": null,
      "description": "",
      "difficult": false,
      "shape_type": "rectangle",
      "flags": {},
      "attributes": {}
    },
    {
      "kie_linking": [],
      "label": "2",
      "score": null,
      "points": [
        [261.66666666666663, 247.08333333333326],
        [292.91666666666663, 247.08333333333326],
        [292.91666666666663, 282.49999999999994],
        [261.66666666666663, 282.49999999999994]
      ],
      "group_id": null,
      "description": "",
      "difficult": false,
      "shape_type": "rectangle",
      "flags": {},
      "attributes": {}
    },
    {
      "kie_linking": [],
      "label": "2",
      "score": null,
      "points": [
        [506.45833333333326, 265.8333333333333],
        [534.5833333333333, 265.8333333333333],
        [534.5833333333333, 302.29166666666663],
        [506.45833333333326, 302.29166666666663]
      ],
      "group_id": null,
      "description": "",
      "difficult": false,
      "shape_type": "rectangle",
      "flags": {},
      "attributes": {}
    },
    {
      "kie_linking": [],
      "label": "2+",
      "score": null,
      "points": [
        [520.0, 578.3333333333333],
        [549.1666666666667, 578.3333333333333],
        [549.1666666666667, 603.3333333333333],
        [520.0, 603.3333333333333]
      ],
      "group_id": null,
      "description": "",
      "difficult": false,
      "shape_type": "rectangle",
      "flags": {},
      "attributes": {}
    }
  ],
  "imagePath": "20240926101529699.bmp",
  "imageData": null,
  "imageHeight": 1240,
  "imageWidth": 1240,
  "description": ""
}
